{
  "city": "miami",
  "city_name": "Miami",
  "date": "2026-04-23",
  "unit": "F",
  "station": "KMIA",
  "event_end_date": "2026-04-23T12:00:00Z",
  "hours_at_discovery": 53.0,
  "status": "resolved",
  "position": {
    "market_id": "2040287",
    "question": "Will the highest temperature in Miami be between 76-77°F on April 23?",
    "bucket_low": 76.0,
    "bucket_high": 77.0,
    "entry_price": 0.13,
    "bid_at_entry": 0.11,
    "spread": 0.02,
    "shares": 38.46,
    "cost": 5.0,
    "p": 1.0,
    "ev": 6.6923,
    "kelly": 0.25,
    "forecast_temp": 76,
    "forecast_src": "hrrr",
    "sigma": 2.0,
    "opened_at": "2026-04-22T04:50:34.179934+00:00",
    "status": "closed",
    "pnl": -5.0,
    "exit_price": 0.0,
    "close_reason": "resolved",
    "closed_at": "2026-04-25T16:24:34.035590+00:00"
  },
  "actual_temp": null,
  "resolved_outcome": "loss",
  "pnl": -5.0,
  "forecast_snapshots": [
    {
      "ts": "2026-04-21T07:00:24.900447+00:00",
      "horizon": "D+2",
      "hours_left": 53.0,
      "ecmwf": 77,
      "hrrr": 78,
      "metar": null,
      "best": 78,
      "best_source": "hrrr"
    },
    {
      "ts": "2026-04-21T14:06:59.978128+00:00",
      "horizon": "D+2",
      "hours_left": 45.9,
      "ecmwf": 76,
      "hrrr": 79,
      "metar": null,
      "best": 79,
      "best_source": "hrrr"
    },
    {
      "ts": "2026-04-21T15:10:56.740122+00:00",
      "horizon": "D+2",
      "hours_left": 44.8,
      "ecmwf": 76,
      "hrrr": 79,
      "metar": null,
      "best": 79,
      "best_source": "hrrr"
    },
    {
      "ts": "2026-04-21T16:18:27.360824+00:00",
      "horizon": "D+2",
      "hours_left": 43.7,
      "ecmwf": 76,
      "hrrr": 79,
      "metar": null,
      "best": 79,
      "best_source": "hrrr"
    },
    {
      "ts": "2026-04-22T04:50:34.179934+00:00",
      "horizon": "D+1",
      "hours_left": 31.2,
      "ecmwf": 77,
      "hrrr": 76,
      "metar": null,
      "best": 76,
      "best_source": "hrrr"
    }
  ],
  "market_snapshots": [
    {
      "ts": "2026-04-21T07:00:24.900447+00:00",
      "top_bucket": "78.0-79.0F",
      "top_price": 0.375
    },
    {
      "ts": "2026-04-21T14:06:59.978128+00:00",
      "top_bucket": "80.0-81.0F",
      "top_price": 0.42
    },
    {
      "ts": "2026-04-21T15:10:56.740122+00:00",
      "top_bucket": "80.0-81.0F",
      "top_price": 0.42
    },
    {
      "ts": "2026-04-21T16:18:27.360824+00:00",
      "top_bucket": "80.0-81.0F",
      "top_price": 0.425
    },
    {
      "ts": "2026-04-22T04:50:34.179934+00:00",
      "top_bucket": "78.0-79.0F",
      "top_price": 0.415
    }
  ],
  "all_outcomes": [
    {
      "question": "Will the highest temperature in Miami be 69°F or below on April 23?",
      "market_id": "2040283",
      "range": [
        -999.0,
        69.0
      ],
      "bid": 0.0015,
      "ask": 0.9985,
      "price": 0.0015,
      "spread": 0.997,
      "volume": 593.0
    },
    {
      "question": "Will the highest temperature in Miami be between 70-71°F on April 23?",
      "market_id": "2040284",
      "range": [
        70.0,
        71.0
      ],
      "bid": 0.005,
      "ask": 0.995,
      "price": 0.005,
      "spread": 0.99,
      "volume": 336.0
    },
    {
      "question": "Will the highest temperature in Miami be between 72-73°F on April 23?",
      "market_id": "2040285",
      "range": [
        72.0,
        73.0
      ],
      "bid": 0.004,
      "ask": 0.996,
      "price": 0.004,
      "spread": 0.992,
      "volume": 322.0
    },
    {
      "question": "Will the highest temperature in Miami be between 74-75°F on April 23?",
      "market_id": "2040286",
      "range": [
        74.0,
        75.0
      ],
      "bid": 0.017,
      "ask": 0.983,
      "price": 0.017,
      "spread": 0.966,
      "volume": 2515.0
    },
    {
      "question": "Will the highest temperature in Miami be between 76-77°F on April 23?",
      "market_id": "2040287",
      "range": [
        76.0,
        77.0
      ],
      "bid": 0.12,
      "ask": 0.88,
      "price": 0.12,
      "spread": 0.76,
      "volume": 1798.0
    },
    {
      "question": "Will the highest temperature in Miami be between 78-79°F on April 23?",
      "market_id": "2040288",
      "range": [
        78.0,
        79.0
      ],
      "bid": 0.415,
      "ask": 0.585,
      "price": 0.415,
      "spread": 0.17,
      "volume": 852.0
    },
    {
      "question": "Will the highest temperature in Miami be between 80-81°F on April 23?",
      "market_id": "2040289",
      "range": [
        80.0,
        81.0
      ],
      "bid": 0.405,
      "ask": 0.595,
      "price": 0.405,
      "spread": 0.19,
      "volume": 759.0
    },
    {
      "question": "Will the highest temperature in Miami be between 82-83°F on April 23?",
      "market_id": "2040290",
      "range": [
        82.0,
        83.0
      ],
      "bid": 0.0305,
      "ask": 0.9695,
      "price": 0.0305,
      "spread": 0.939,
      "volume": 2016.0
    },
    {
      "question": "Will the highest temperature in Miami be between 84-85°F on April 23?",
      "market_id": "2040291",
      "range": [
        84.0,
        85.0
      ],
      "bid": 0.013,
      "ask": 0.987,
      "price": 0.013,
      "spread": 0.974,
      "volume": 323.0
    },
    {
      "question": "Will the highest temperature in Miami be between 86-87°F on April 23?",
      "market_id": "2040292",
      "range": [
        86.0,
        87.0
      ],
      "bid": 0.008,
      "ask": 0.992,
      "price": 0.008,
      "spread": 0.984,
      "volume": 303.0
    },
    {
      "question": "Will the highest temperature in Miami be 88°F or higher on April 23?",
      "market_id": "2040293",
      "range": [
        88.0,
        999.0
      ],
      "bid": 0.003,
      "ask": 0.997,
      "price": 0.003,
      "spread": 0.994,
      "volume": 2095.0
    }
  ],
  "created_at": "2026-04-21T07:00:30.817853+00:00"
}